setup.cfg
setup.py
psynth/__init__.py
psynth/psynth.py
psynth.egg-info/PKG-INFO
psynth.egg-info/SOURCES.txt
psynth.egg-info/dependency_links.txt
psynth.egg-info/requires.txt
psynth.egg-info/top_level.txt