Metadata-Version: 1.1
Name: psynth
Version: 0.1.3
Summary: The official open-source Python library for generating graphs in Psymphonic Psynth.
Home-page: http://shawnrushefsky.github.io/python_psynth
Author: Psymphonic
Author-email: shawn@psymphonic.com
License: MIT
Download-URL: https://github.com/shawnrushefsky/python_psynth.git
Keywords: psynth,psymphonic,graph,graphdb,visualize,network
Platform: UNKNOWN
Classifier: Development Status :: 4 - Beta
Classifier: License :: OSI Approved :: MIT License
Classifier: Intended Audience :: Developers
Classifier: Intended Audience :: Education
Classifier: Intended Audience :: Financial and Insurance Industry
Classifier: Intended Audience :: Healthcare Industry
Classifier: Intended Audience :: Information Technology
Classifier: Intended Audience :: Science/Research
Classifier: Intended Audience :: System Administrators
Classifier: Intended Audience :: Telecommunications Industry
Classifier: Natural Language :: English
Classifier: Programming Language :: Python :: 2.7
Classifier: Topic :: Database :: Front-Ends
Classifier: Topic :: Education
Classifier: Topic :: Multimedia :: Graphics :: Presentation
Classifier: Topic :: Office/Business :: Financial :: Spreadsheet
Classifier: Topic :: Scientific/Engineering :: Visualization
Classifier: Topic :: Software Development :: Libraries
